prana_rc/__init__.py
prana_rc/__main__.py
prana_rc/__version__.py
prana_rc/cli.py
prana_rc/cli_utils.py
prana_rc/entity.py
prana_rc/service.py
prana_rc/utils.py
prana_rc/contrib/__init__.py
prana_rc/contrib/api/__init__.py
prana_rc/contrib/api/dto.py
prana_rc/contrib/api/handler.py
prana_rc/contrib/client/__init__.py
prana_rc/contrib/client/aiohttp.py
prana_rc/contrib/client/common.py
prana_rc/contrib/http_server/__init__.py
prana_rc/contrib/http_server/cli.py
prana_rc-0.4.4.dist-info/METADATA
prana_rc-0.4.4.dist-info/WHEEL
prana_rc-0.4.4.dist-info/entry_points.txt
prana_rc-0.4.4.dist-info/top_level.txt
prana_rc-0.4.4.dist-info/RECORD
